MANIFEST.in
README.md
setup.py
skypipe/__init__.py
skypipe/cli.py
skypipe/client.py
skypipe/cloud.py
skypipe.egg-info/PKG-INFO
skypipe.egg-info/SOURCES.txt
skypipe.egg-info/dependency_links.txt
skypipe.egg-info/entry_points.txt
skypipe.egg-info/not-zip-safe
skypipe.egg-info/requires.txt
skypipe.egg-info/top_level.txt
skypipe/satellite/builder
skypipe/satellite/dotcloud.yml
skypipe/satellite/requirements.txt
skypipe/satellite/server.py