Metadata-Version: 1.1
Name: skypipe
Version: 0.1.4
Summary: Magic pipe in the sky
Home-page: http://github.com/progrium/skypipe
Author: Jeff Lindsay
Author-email: progrium@gmail.com
License: MIT
Platform: UNKNOWN
Classifier: Development Status :: 3 - Alpha
Classifier: Topic :: Utilities
Classifier: License :: OSI Approved :: MIT License
